test.py
PySideUI/__init__.py
PySideUI/components/__init__.py
PySideUI/components/button.py
PySideUI/utils/attrs.py
PySideUI-0.0.3.dist-info/LICENSE
PySideUI-0.0.3.dist-info/METADATA
PySideUI-0.0.3.dist-info/WHEEL
PySideUI-0.0.3.dist-info/top_level.txt
PySideUI-0.0.3.dist-info/RECORD
