Metadata-Version: 2.1
Name: PySideUI
Version: 0.0.3
Summary: A UI library for PySide
Author-email: Arthur Chan <chenzhiguook@foxmail.com>
Project-URL: Homepage, https://github.com/arthurchen1906/PySideUI
Project-URL: Bug Tracker, https://github.com/arthurchen1906/PySideUI/issues
Classifier: Programming Language :: Python :: 3
Classifier: License :: OSI Approved :: MIT License
Classifier: Operating System :: OS Independent
Requires-Python: >=3.8
License-File: LICENSE
